fasttrees/__init__.py
fasttrees/fasttrees.py
fasttrees-1.3.1.dist-info/LICENSE.txt
fasttrees-1.3.1.dist-info/METADATA
fasttrees-1.3.1.dist-info/WHEEL
fasttrees-1.3.1.dist-info/top_level.txt
fasttrees-1.3.1.dist-info/RECORD
