Metadata-Version: 2.1
Name: fasttrees
Version: 1.3.1
Summary: A fast and frugal tree classifier for sklearn
Home-page: https://github.com/fasttrees/fasttrees
Author: Dominic Zijlstra, Stefan Bachhofner
Author-email: dominiczijlstra@gmail.com, bachhofner.dev@gmail.com
License: MIT License
Project-URL: Documentation, https://fasttrees.github.io/fasttrees
Project-URL: Source, https://github.com/fasttrees/fasttrees
Project-URL: Tracker, https://github.com/fasttrees/fasttrees/issues
Classifier: License :: OSI Approved :: MIT License
Classifier: Intended Audience :: Science/Research
Classifier: Intended Audience :: Developers
Classifier: Topic :: Software Development
Classifier: Topic :: Scientific/Engineering
Classifier: Programming Language :: Python
Classifier: Programming Language :: Python :: 3
Classifier: Programming Language :: Python :: 3 :: Only
Classifier: Programming Language :: Python :: 3.8
Requires-Python: >=3.8
License-File: LICENSE.txt
Requires-Dist: numpy <=1.19.5
Requires-Dist: pandas <=0.25.3
Requires-Dist: scikit-learn <=0.23.2
